rolos/__init__.py
rolos-0.1.0.dist-info/LICENSE
rolos-0.1.0.dist-info/WHEEL
rolos-0.1.0.dist-info/METADATA
rolos-0.1.0.dist-info/RECORD
